djsommo/__init__.py
djsommo-0.2.1.dist-info/LICENSE
djsommo-0.2.1.dist-info/METADATA
djsommo-0.2.1.dist-info/WHEEL
djsommo-0.2.1.dist-info/top_level.txt
djsommo-0.2.1.dist-info/version.txt
djsommo-0.2.1.dist-info/zip-safe
djsommo-0.2.1.dist-info/RECORD
